{
    "trade": {
        "tradeIdentifier": [
            {
                "issuerReference": {
                    "globalReference": "95918657",
                    "externalReference": "33f59567"
                },
                "assignedIdentifier": [
                    {
                        "identifier": {
                            "value": "1234",
                            "meta": {
                                "scheme": "ISDA"
                            }
                        }
                    }
                ]
            }
        ],
        "tradeDate": {
            "value": "1234",
            "meta": {
                "globalKey": "95918657",
                "externalKey": "95918657"
            }
        },
        "tradableProduct": {
            "product": {
                "contractualProduct": {
                    "economicTerms": {
                        "payout": {
                            "optionPayout": [
                                {
                                    "buyerSeller": {
                                        "buyer": "Party1",
                                        "seller": "Party2"
                                    },
                                    "underlier": {
                                        "index": {
                                            "productIdentifier": [
                                                {
                                                    "address": {
                                                        "scope": "",
                                                        "value": ""
                                                    }
                                                }
                                            ]
                                        },
                                        "security": {
                                            "securityType": "Basket Option",
                                            "productIdentifier": [
                                                {
                                                    "address": {
                                                        "scope": "Basket of Equities",
                                                        "value": "Basket of Equities (product identifiers: productIdentifier-2, productIdentifier-3)"
                                                    }
                                                },
                                                {
                                                    "address": {
                                                        "scope": "Equities",
                                                        "value": "Equities (product identifiers: productIdentifier-4, productIdentifier-5, productIdentifier-1, productIdentifier-6)"
                                                    }
                                                }
                                            ]
                                        },
                                        "basket": {
                                            "basketConstituent": [
                                                {
                                                    "index": {
                                                        "productIdentifier": [
                                                            {
                                                                "address": {
                                                                    "scope": "",
                                                                    "value": ""
                                                                }
                                                            }
                                                        ]
                                                    },
                                                    "security": {
                                                        "securityType": "",
                                                        "productIdentifier": [
                                                            {
                                                                "address": {
                                                                    "scope": "",
                                                                    "value": ""
                                                                }
                                                            }
                                                        ]
                                                    },
                                                    "basket": {
                                                        "basketConstituent": [
                                                            {
                                                                "security": {
                                                                    "securityType": "",
                                                                    "productIdentifier": [
                                                                        {
                                                                            "address": {
                                                                                "scope": "",
                                                                                "value": ""
                                                                            }
                                                                        }
                                                                    ]
                                                                }
                                                            }
                                                        ]
                                                    }
                                                }
                                            ]
                                        }
                                    },
                                    "optionType": "Based on the provided inputs, I will populate the placeholder with the best-suited information from the contract description and prior context.\n\n### Inputs:\n\n* Key: optionType\n* Placeholder: `{{optionType}}`\n* Derivatives Contract Description:\n    **Contract Description**\n\n    This contract is a derivative transaction between Party A (Party1) and Party B (Party2) for a basket option on a basket of equities. The trade date is July 13, 2001, and the trade identifier is 1234.\n\n    **Trade Details**\n\n    * Trade Date: July 13, 2001\n    * Trade Identifier: 1234\n    * Issuer Reference: 33f59567\n    * Assigned Identifier: 1234\n    * Global Key: 95918657\n\n    **Trade Product**\n\n    * Product Type: Basket Option\n    * Underlier: Basket of Equities\n    * Basket Constituents:\n        + Index: Basket of Equities (product identifiers: productIdentifier-2, productIdentifier-3)\n        + Securities: Equities (product identifiers: productIdentifier-4, productIdentifier-5, productIdentifier-1, productIdentifier-6)\n    * Option Type: Call\n    * Strike Price: 32.00 EUR\n    * Exercise Terms:\n        + Style: American\n        + Commencement Date: July 13, 2001\n        + Expiration Date: September 27, 2005\n        + Latest Exercise Time: 17:15:00 (GBLO)\n        + Multiple Exercise: 1-150,000 options\n        + Automatic Exercise: Applicable\n\n    **Trade Lot**\n\n    * Price Quantity:\n        + Quantity: 150,000 contracts\n        + Unit: Contract\n        + Multiplier: 1.00\n    * Observable:\n        + Product Identifier: FXI (identifier: FXI, source: Other)\n        + Product Identifier: FTSE/Xinhua China 25 Index (identifier: FTSE/Xinhua China 25 Index, source: Name)\n        + Quantity: 0.50 weights\n        + Unit: Weight\n        + Product Identifier: 005440.KS (identifier: 005440.KS, source: Other)\n        + Product Identifier: HYUNDAI MOTOR COMPANY (identifier: HYUNDAI MOTOR COMPANY, source: Name)\n        + Quantity: 0.25 weights\n        + Unit: Weight\n        + Product Identifier: 000270.KS (identifier: 000270.KS, source: Other)\n        + Product Identifier: KIA MOTORS CORPORATION (identifier: KIA MOTORS CORPORATION, source: Name)\n\n    **Counterparty**\n\n    * Party A: Party1\n    * Party B: Party2\n\n    **Contract Details**\n\n    * Governing Law: GBEN\n    * Documentation: ISDA\n    * Calculation Agent: CalculationAgentIndependent\n    * Governing Law: Province of Ontario and the laws of Canada applicable therein\n\n    **Transfer History**\n\n    * Transfer Date: July 17, 2001\n    * Quantity: 405,000 EUR\n    * Asset: Cash\n    * Payer/Receiver: Party2 (payer) and Party1 (receiver)\n    * Settlement Date: July 17, 2001\n    * Transfer Expression: Premium\n\n### Prior Context (Path):\ntrade.tradableProduct.product.contractualProduct.economicTerms.payout.optionPayout[0].optionType\n\n### Output:\n\n* Key: optionType\n* Placeholder: `{{optionType}}`\n* Value: Call\n\nThe `optionType` key in the contract description corresponds to the value \"Call\". This value is best suited for the provided key and prior context.",
                                    "exerciseTerms": {
                                        "style": "American",
                                        "commencementDate": {
                                            "adjustableDate": {
                                                "unadjustedDate": "July 13, 2001",
                                                "dateAdjustments": {
                                                    "businessDayConvention": "Following"
                                                }
                                            }
                                        },
                                        "expirationDate": [
                                            {
                                                "adjustableDate": {
                                                    "unadjustedDate": "September 27, 2005",
                                                    "dateAdjustments": {
                                                        "businessDayConvention": "Following"
                                                    }
                                                }
                                            }
                                        ],
                                        "latestExerciseTime": {
                                            "hourMinuteTime": "17:15:00",
                                            "businessCenter": {
                                                "value": "GBLO"
                                            }
                                        },
                                        "expirationTimeType": "",
                                        "multipleExercise": {
                                            "maximumNumberOfOptions": 150000,
                                            "integralMultipleAmount": 1,
                                            "minimumNumberOfOptions": 1
                                        },
                                        "exerciseProcedure": {
                                            "automaticExercise": {
                                                "isApplicable": true
                                            }
                                        }
                                    },
                                    "strike": {
                                        "strikePrice": {
                                            "perUnitOf": {
                                                "financialUnit": "EUR",
                                                "priceType": "STRIKE",
                                                "value": "32.00",
                                                "unit": {
                                                    "currency": {
                                                        "value": "EUR"
                                                    }
                                                }
                                            }
                                        }
                                    },
                                    "payerReceiver": {
                                        "payer": "Party1",
                                        "receiver": "Party2"
                                    },
                                    "priceQuantity": {
                                        "quantitySchedule": {
                                            "address": {
                                                "scope": "",
                                                "value": ""
                                            }
                                        }
                                    },
                                    "settlementTerms": {
                                        "settlementType": "Cash",
                                        "settlementCurrency": {
                                            "value": "EUR"
                                        },
                                        "settlementDate": {
                                            "adjustableOrRelativeDate": {
                                                "relativeDate": {
                                                    "businessDayConvention": "",
                                                    "dateRelativeTo": {
                                                        "externalReference": ""
                                                    },
                                                    "dayType": "",
                                                    "periodMultiplier": null,
                                                    "period": ""
                                                }
                                            }
                                        }
                                    }
                                }
                            ]
                        },
                        "calculationAgent": {
                            "calculationAgentParty": [
                                {
                                    "party": "Party1",
                                    "partyType": "Counterparty",
                                    "partyIdentifier": "Party1",
                                    "partyRole": "Calculation Agent"
                                },
                                {
                                    "party": "Party2",
                                    "partyType": "Counterparty",
                                    "partyIdentifier": "Party2",
                                    "partyRole": "Calculation Agent"
                                }
                            ]
                        }
                    },
                    "productTaxonomy": [
                        {
                            "productQualifier": "",
                            "source": "Other",
                            "value": {
                                "name": {
                                    "value": "Basket of Equities"
                                }
                            }
                        }
                    ]
                }
            },
            "tradeLot": [
                {
                    "priceQuantity": [
                        {
                            "quantity": [
                                {
                                    "value": null,
                                    "unit": {
                                        "financialUnit": ""
                                    }
                                }
                            ],
                            "observable": {
                                "commodity": {
                                    "value": {
                                        "priceQuoteType": "FXI",
                                        "deliveryDateReference": {
                                            "deliveryNearby": {
                                                "periodMultiplier": null,
                                                "period": "Calendar Days"
                                            }
                                        }
                                    }
                                },
                                "productIdentifier": {
                                    "value": {
                                        "identifier": {
                                            "value": "95918657",
                                            "meta": {
                                                "scheme": "ISDA"
                                            }
                                        },
                                        "source": "Other"
                                    }
                                }
                            }
                        }
                    ]
                }
            ],
            "counterparty": {
                "role": "Payer",
                "partyReference": {
                    "globalReference": "95918657",
                    "externalReference": "1234"
                }
            },
            "ancillaryParty": {
                "role": "Buyer",
                "partyReference": [
                    {
                        "globalReference": "95918657",
                        "externalReference": "Party1"
                    },
                    {
                        "globalReference": "95918657",
                        "externalReference": "Party2"
                    }
                ]
            }
        },
        "party": [
            {
                "partyId": [
                    {
                        "identifier": {
                            "value": "Party1",
                            "meta": {
                                "scheme": "ISDA"
                            }
                        }
                    },
                    {
                        "identifier": {
                            "value": "Party2",
                            "meta": {
                                "scheme": "ISDA"
                            }
                        }
                    }
                ]
            }
        ],
        "contractDetails": {
            "documentation": [
                {
                    "agreementDate": "2001-07-13",
                    "legalAgreementIdentification": {
                        "agreementName": {
                            "agreementType": "Basket Option",
                            "contractualDefinitionsType": [
                                {
                                    "value": "English Law"
                                }
                            ],
                            "masterAgreementType": {
                                "value": "ISDA 2013 Standard Credit Support Annex"
                            }
                        },
                        "vintage": "2001-07-13"
                    },
                    "contractualParty": [
                        {
                            "globalReference": "Party1",
                            "externalReference": ""
                        },
                        {
                            "globalReference": "Party2",
                            "externalReference": ""
                        }
                    ]
                }
            ],
            "governingLaw": {
                "value": "GBEN"
            }
        }
    }
}